autopr/__init__.py
autopr/ai_service.py
autopr/cli.py
autopr/git_utils.py
autopr/github_service.py
tests/__init__.py
tests/test_ai_service.py
tests/test_cli.py
tests/test_git_utils.py
tests/test_github_service.py
autopr_cli-0.2.28.dist-info/METADATA
autopr_cli-0.2.28.dist-info/WHEEL
autopr_cli-0.2.28.dist-info/entry_points.txt
autopr_cli-0.2.28.dist-info/top_level.txt
autopr_cli-0.2.28.dist-info/RECORD
