Metadata-Version: 2.4
Name: autopr_cli
Version: 0.2.28
Summary: A CLI tool to automate PR creation and listing.
Home-page: https://github.com/leaopedro/autopr
Author: Pedro Leao
Author-email: leaop54@gmail.com
Classifier: Programming Language :: Python :: 3
Classifier: License :: OSI Approved :: MIT License
Classifier: Operating System :: OS Independent
Requires-Python: >=3.6
Dynamic: author
Dynamic: author-email
Dynamic: classifier
Dynamic: description
Dynamic: description-content-type
Dynamic: home-page
Dynamic: requires-python
Dynamic: summary
